dlg_nifty_components/__init__.py
dlg_nifty_components/cpu_gridder.py
dlg_nifty_components/cuda_gridder.py
dlg_nifty_components/degridder.py
dlg_nifty_components/gridder.py
dlg_nifty_components-1.1.0.dist-info/LICENSE
dlg_nifty_components-1.1.0.dist-info/METADATA
dlg_nifty_components-1.1.0.dist-info/WHEEL
dlg_nifty_components-1.1.0.dist-info/top_level.txt
dlg_nifty_components-1.1.0.dist-info/RECORD
