Metadata-Version: 2.1
Name: dlg-nifty-components
Version: 1.1.0
Summary: nifty gridding components for daliuge-engine created by ICRAR
Home-page: https://github.com/ICRAR/dlg-nifty-components
Author: ICRAR DIA Group
Author-email: dfms_prototype@googlegroups.com
License: BSD License
Platform: UNKNOWN
License-File: LICENSE
Requires-Dist: daliuge-engine (>=2.1.0)
Requires-Dist: numpy (>=1.20.0)
Requires-Dist: ducc0 (>=0.21.0)
Provides-Extra: cuda
Requires-Dist: ska-gridder-nifty-cuda (>=0.3.0) ; extra == 'cuda'
Provides-Extra: test
Requires-Dist: pytest ; extra == 'test'
Requires-Dist: coverage ; extra == 'test'
Requires-Dist: flake8 ; extra == 'test'
Requires-Dist: black ; extra == 'test'
Requires-Dist: isort ; extra == 'test'
Requires-Dist: pytest-cov ; extra == 'test'
Requires-Dist: codecov ; extra == 'test'
Requires-Dist: mypy ; extra == 'test'
Requires-Dist: gitchangelog ; extra == 'test'
Requires-Dist: mkdocs ; extra == 'test'
